pyElevenlabs/__init__.py
pyElevenlabs/pyElevenlabs.py
pyElevenlabs/test.py
pyElevenlabs-0.0.3.dist-info/LICENSE
pyElevenlabs-0.0.3.dist-info/METADATA
pyElevenlabs-0.0.3.dist-info/WHEEL
pyElevenlabs-0.0.3.dist-info/top_level.txt
pyElevenlabs-0.0.3.dist-info/RECORD
