Metadata-Version: 2.1
Name: pyElevenlabs
Version: 0.0.3
Summary: Python wrapper for the ElevenLabs API
Author-email: Philip Lawall <philip@lawall.me>
Project-URL: Homepage, https://github.com/philiplawall/pyElevenLabs
Project-URL: Bug Tracker, https://github.com/philiplawall/pyElevenLabs/issues
Classifier: Programming Language :: Python :: 3
Classifier: License :: OSI Approved :: MIT License
Classifier: Operating System :: OS Independent
Requires-Python: >=3.6
License-File: LICENSE
